docs/generators/lastpass.md
docs/modules/cubizoid.md
docs/modules/files.md
docs/transformers/embed.md
docs/transformers/replicate.md
docs/tutorials/extend_kube_tools.md
examples/embed/container.json
examples/embed/embed.yaml
examples/embed/kustomization.yaml
examples/embed/pod.yaml
examples/embed/some.sh
examples/embed/some.yaml
examples/envmapper/set-env.yaml
examples/kompose/docker-compose.yml
examples/kompose/kompose.yaml
examples/kompose/kustomization.yaml
examples/krm/kustomization.yaml
examples/krm/test-krm.py
examples/krm/test-krm.yaml
examples/lastpass/example.yaml
examples/lastpass/kustomization.yaml
examples/listify/kustomization.yaml
examples/listify/listify.yaml
examples/listify/some-list.yaml
examples/replicate/README.md
examples/replicate/conf.yaml
examples/replicate/generated.yaml
examples/replicate/kustomization.yaml
examples/replicate/multiply.yaml
examples/replicate/some-app.yaml
kubed/__init__.py
kubed/konfig/__init__.py
kubed/konfig/lastpass.yaml
kubed/krm/__init__.py
kubed/krm/cli.py
kubed/krm/common.py
kubed/krm/common_test.py
kubed/krm/errors.py
kubed/krm/files.py
kubed/krm/k8s.py
kubed/krm/model.py
kubed/krm/util.py
kubed/kubectl/__init__.py
kubed/kubectl/envmap.py
kubed/kubectl/envmap_test.py
kubed/kustomize/__init__.py
kubed/kustomize/embed.py
kubed/kustomize/lastpass.py
kubed/kustomize/replicate.py
kubed/kustomize/replicate_test.py
kubed/kustomize/filter/__init__.py
kubed_krm-0.0.2.dist-info/licenses/LICENSE
kubed_krm-0.0.2.dist-info/METADATA
kubed_krm-0.0.2.dist-info/WHEEL
kubed_krm-0.0.2.dist-info/entry_points.txt
kubed_krm-0.0.2.dist-info/top_level.txt
kubed_krm-0.0.2.dist-info/RECORD
